{
  "$schema": "https://raw.githubusercontent.com/Cencosud-X/seki-schemas/main/v1/cloud/componentrc.schema.json",
  "name": "AWS SQS QUEUE",
  "kind": "aws_sqs",
  "owner": ["bushido"],
  "visibility": "internal",
  "tags": [
    "SQS",
    "Queue",
    "FIFO",
    "AWS",
    "experimental"
  ],
  "icons": {
    "light": "icons/icon-white.svg",
    "dark": "icons/icon.svg"
  },
  "short_descriptions": {
    "es": "Cola de Mensajes SQS",
    "en": "SQS Queue Message"
  },
  "descriptions": {
    "es": "Es uno de los servicios ofrecidos por la infraestructura de AWS y se enfoca en el manejo de las colas de mensajes",
    "en": "It is one of the services offered by AWS infrastructure and focuses on message queue management."
  },
  "scripts": {
    "rollback": "scripts/rollback.js"
  },
  "interpolations": {
    "source": "template"
  },
  "output": "settings.json"
}
